odoo/addons/server_environment_ir_config_parameter/README.rst
odoo/addons/server_environment_ir_config_parameter/__init__.py
odoo/addons/server_environment_ir_config_parameter/__manifest__.py
odoo/addons/server_environment_ir_config_parameter/i18n/de.po
odoo/addons/server_environment_ir_config_parameter/i18n/es.po
odoo/addons/server_environment_ir_config_parameter/i18n/it.po
odoo/addons/server_environment_ir_config_parameter/i18n/nl_NL.po
odoo/addons/server_environment_ir_config_parameter/i18n/ro.po
odoo/addons/server_environment_ir_config_parameter/models/__init__.py
odoo/addons/server_environment_ir_config_parameter/models/ir_config_parameter.py
odoo/addons/server_environment_ir_config_parameter/tests/__init__.py
odoo/addons/server_environment_ir_config_parameter/tests/config_param_test.xml
odoo/addons/server_environment_ir_config_parameter/tests/test_server_environment_ircp.py
odoo11_addon_server_environment_ir_config_parameter-11.0.1.0.0.dist-info/DESCRIPTION.rst
odoo11_addon_server_environment_ir_config_parameter-11.0.1.0.0.dist-info/METADATA
odoo11_addon_server_environment_ir_config_parameter-11.0.1.0.0.dist-info/RECORD
odoo11_addon_server_environment_ir_config_parameter-11.0.1.0.0.dist-info/WHEEL
odoo11_addon_server_environment_ir_config_parameter-11.0.1.0.0.dist-info/metadata.json
odoo11_addon_server_environment_ir_config_parameter-11.0.1.0.0.dist-info/top_level.txt
